flagtest/__init__.py
flagtest/data.py
flagtest/flagmoji.py
flagtest-1.2.dist-info/METADATA
flagtest-1.2.dist-info/WHEEL
flagtest-1.2.dist-info/top_level.txt
flagtest-1.2.dist-info/RECORD
