Metadata-Version: 2.1
Name: flagtest
Version: 1.2
Summary: Converts a country code or country name into a flag emoji
Home-page: https://github.com/stevenyuser/flagmoji
Author: Steven Yu
Author-email: stevenyuser@gmail.com
License: UNKNOWN
Keywords: python,flagmoji,emoji flag converter
Platform: UNKNOWN
Classifier: Development Status :: 3 - Alpha
Classifier: Intended Audience :: Education
Classifier: Programming Language :: Python :: 2
Classifier: Programming Language :: Python :: 3
Classifier: Operating System :: MacOS :: MacOS X
Classifier: Operating System :: Microsoft :: Windows
